nhncloud_email/__init__.py
nhncloud_email/email.py
tests/__init__.py
tests/tests_helper.py
tests/helpers/__init__.py
tests/helpers/my_helper.py
tests/unit/__init__.py
tests/unit/test_email.py
nhncloud_email-0.1.8.dist-info/LICENSE
nhncloud_email-0.1.8.dist-info/METADATA
nhncloud_email-0.1.8.dist-info/WHEEL
nhncloud_email-0.1.8.dist-info/top_level.txt
nhncloud_email-0.1.8.dist-info/RECORD
