Metadata-Version: 2.1
Name: nhncloud-email
Version: 0.1.8
Summary: A Python library to send Email using NHN Cloud API
Home-page: https://github.com/RUNNERS-IM/python-nhncloud-email
Author: RUNNERS
Author-email: dev@runners.im
License: UNKNOWN
Platform: UNKNOWN
Classifier: Environment :: Web Environment
Classifier: Intended Audience :: Developers
Classifier: License :: OSI Approved :: MIT License
Classifier: Operating System :: OS Independent
Classifier: Programming Language :: Python
Classifier: Programming Language :: Python :: 3
Classifier: Topic :: Software Development :: Libraries :: Python Modules
Requires-Dist: requests
